github_wiki_edit_url/__init__.py
github_wiki_edit_url/plugin.py
mkdocs_github_wiki_edit_url-0.4.dist-info/METADATA
mkdocs_github_wiki_edit_url-0.4.dist-info/WHEEL
mkdocs_github_wiki_edit_url-0.4.dist-info/entry_points.txt
mkdocs_github_wiki_edit_url-0.4.dist-info/top_level.txt
mkdocs_github_wiki_edit_url-0.4.dist-info/RECORD
