Metadata-Version: 2.1
Name: mkdocs-github-wiki-edit-url
Version: 0.4
Summary: Use Edit URLs compatible with GitHub Wiki
Home-page: https://github.com/MichelZ/mkdocs-github-wiki-edit-url
Author: Michel Zehnder
License: MIT
